setup.cfg
setup.py
sofiia_rada_package/__init__.py
sofiia_rada_package/descriptors.py
sofiia_rada_package/rada_consoles.py
sofiia_rada_package/rada_databases.py
sofiia_rada_package/rada_factories.py
sofiia_rada_package/rada_metaclass.py
sofiia_rada_package/rada_models.py
sofiia_rada_package/utils.py
sofiia_rada_package/verh_rada.py
sofiia_rada_package.egg-info/PKG-INFO
sofiia_rada_package.egg-info/SOURCES.txt
sofiia_rada_package.egg-info/dependency_links.txt
sofiia_rada_package.egg-info/entry_points.txt
sofiia_rada_package.egg-info/not-zip-safe
sofiia_rada_package.egg-info/top_level.txt