Metadata-Version: 1.0
Name: sofiia-rada-package
Version: 0.2.dev0
Summary: Sofiia's Verhovna Rada
Home-page: UNKNOWN
Author: Sofiia Kopach
Author-email: sofiia.kopach@gmail.com
License: UNKNOWN
Platform: UNKNOWN
